uszipcensus/__init__.py
uszipcensus/helpers/divisions.py
uszipcensus/helpers/regions.py
uszipcensus/main.py
us_zip_census-0.1.5.dist-info/METADATA
us_zip_census-0.1.5.dist-info/WHEEL
us_zip_census-0.1.5.dist-info/RECORD
