Metadata-Version: 2.3
Name: us-zip-census
Version: 0.1.5
Summary: A package for converting US ZIP code to US Census Region and Division
License: MIT
Author: Kris Szczepaniak
Author-email: kris.szczepaniak@outlook.com
Requires-Python: >=3.9
Classifier: License :: OSI Approved :: MIT License
Classifier: Programming Language :: Python :: 3
Classifier: Programming Language :: Python :: 3.9
Classifier: Programming Language :: Python :: 3.10
Classifier: Programming Language :: Python :: 3.11
Classifier: Programming Language :: Python :: 3.12
Classifier: Programming Language :: Python :: 3.13
Requires-Dist: zipcodes (>=1.3.0,<2.0.0)
